makeshift/__init__.py
makeshift/__main__.py
makeshift/ast_printer.py
makeshift/file_printer.py
makeshift/scratch.py
makeshift/interpreter/__init__.py
makeshift/interpreter/ast.py
makeshift/interpreter/interpreter.py
makeshift/interpreter/lexer.py
makeshift/interpreter/parser.py
makeshift/interpreter/token.py
makeshift/interpreter/utils.py
makeshift-0.0.1.dist-info/LICENSE
makeshift-0.0.1.dist-info/METADATA
makeshift-0.0.1.dist-info/WHEEL
makeshift-0.0.1.dist-info/entry_points.txt
makeshift-0.0.1.dist-info/top_level.txt
makeshift-0.0.1.dist-info/RECORD
