Metadata-Version: 2.1
Name: makeshift
Version: 0.0.1
Summary: Procedural text generation based on phrase templates.
Author-email: Michael Joseph <josco.michael@gmail.com>
License: MIT License
Project-URL: Homepage, https://github.com/MJoseph1234/makeshift
Project-URL: Source, https://github.com/MJoseph1234/makeshift
Classifier: Development Status :: 2 - Pre-Alpha
Classifier: License :: OSI Approved :: MIT License
Requires-Python: >=3.11
License-File: LICENSE
